talklib/__init__.py
talklib/cli.py
talklib/ev.py
talklib/ffmpeg.py
talklib/notify.py
talklib/pod.py
talklib/show.py
talklib/utils.py
talklib-3.4.5.dist-info/licenses/LICENSE.txt
talklib-3.4.5.dist-info/METADATA
talklib-3.4.5.dist-info/WHEEL
talklib-3.4.5.dist-info/entry_points.txt
talklib-3.4.5.dist-info/top_level.txt
talklib-3.4.5.dist-info/RECORD
