Metadata-Version: 2.4
Name: talklib
Version: 3.4.5
Summary: A package to automate processing of shows/segments airing on the TL
Author-email: Ben Weddle <ben.weddle@gmail.com>
Maintainer-email: Ben Weddle <ben.weddle@gmail.com>
License-Expression: MIT-open-group
Project-URL: Repository, https://github.com/talkinglibrary/talklib
Project-URL: Issues, https://github.com/talkinglibrary/talklib/issues
Requires-Python: >=3.10
License-File: LICENSE.txt
Requires-Dist: aiohappyeyeballs==2.4.0
Requires-Dist: aiohttp==3.10.5
Requires-Dist: aiohttp-retry==2.8.3
Requires-Dist: aiosignal==1.3.1
Requires-Dist: annotated-types==0.7.0
Requires-Dist: async-timeout==4.0.2
Requires-Dist: attrs==22.1.0
Requires-Dist: bcrypt==4.2.0
Requires-Dist: boto3==1.35.18
Requires-Dist: botocore==1.35.18
Requires-Dist: build==1.0.3
Requires-Dist: certifi==2024.8.30
Requires-Dist: cffi==1.17.1
Requires-Dist: charset-normalizer==2.1.1
Requires-Dist: colorama==0.4.6
Requires-Dist: coverage==6.5.0
Requires-Dist: cryptography==43.0.3
Requires-Dist: decorator==5.1.1
Requires-Dist: Deprecated==1.2.14
Requires-Dist: docutils==0.20.1
Requires-Dist: exceptiongroup==1.0.4
Requires-Dist: fabric==3.2.2
Requires-Dist: ffmpeg-python==0.2.0
Requires-Dist: frozenlist==1.4.1
Requires-Dist: future==0.18.3
Requires-Dist: idna==3.4
Requires-Dist: importlib-metadata==7.0.1
Requires-Dist: iniconfig==1.1.1
Requires-Dist: invoke==2.2.0
Requires-Dist: jaraco.classes==3.3.0
Requires-Dist: jmespath==1.0.1
Requires-Dist: keyring==24.3.0
Requires-Dist: markdown-it-py==3.0.0
Requires-Dist: mdurl==0.1.2
Requires-Dist: more-itertools==10.2.0
Requires-Dist: multidict==6.0.4
Requires-Dist: nh3==0.2.15
Requires-Dist: packaging==21.3
Requires-Dist: paramiko==3.5.0
Requires-Dist: pkginfo==1.9.6
Requires-Dist: pluggy==1.0.0
Requires-Dist: pycparser==2.22
Requires-Dist: pydantic==2.9.1
Requires-Dist: pydantic_core==2.23.3
Requires-Dist: Pygments==2.17.2
Requires-Dist: PyJWT==2.6.0
Requires-Dist: PyNaCl==1.5.0
Requires-Dist: pyparsing==3.0.9
Requires-Dist: pyproject_hooks==1.0.0
Requires-Dist: pytest==7.2.0
Requires-Dist: pytest-cov==4.0.0
Requires-Dist: python-dateutil==2.9.0.post0
Requires-Dist: pytz==2022.6
Requires-Dist: pywin32-ctypes==0.2.2
Requires-Dist: readme-renderer==42.0
Requires-Dist: requests==2.32.3
Requires-Dist: requests-toolbelt==1.0.0
Requires-Dist: rfc3986==2.0.0
Requires-Dist: rich==13.7.0
Requires-Dist: s3transfer==0.10.2
Requires-Dist: six==1.16.0
Requires-Dist: tomli==2.0.1
Requires-Dist: twilio==9.0.2
Requires-Dist: twine==4.0.2
Requires-Dist: typing_extensions==4.12.2
Requires-Dist: urllib3==2.2.2
Requires-Dist: wrapt==1.16.0
Requires-Dist: yarl==1.9.2
Requires-Dist: zipp==3.17.0
Dynamic: license-file
